[
    {
        "title": "Anime X Game Festival 2024 - 일반 입장권",
        "ImageURL": "http://tkfile.yes24.com/upload2/perfblog/202410/20241024/20241024-51251.jpg",
        "Venue": "2024.12.07~2024.12.08KINTEX 제1전시장 1/2/3/4/5 HALL",
        "rank": "1위",
        "site": "http://ticket.yes24.com/Rank/All",
        "change": "-"
    },
    {
        "title": "[서울] 강철의 연금술사전",
        "ImageURL": "http://tkfile.yes24.com/upload2/perfblog/202411/20241129/20241129-51195.jpg",
        "Venue": "2024.11.30~2025.03.03DUEX 홍대 1관",
        "rank": "2위",
        "site": "http://ticket.yes24.com/Rank/All",
        "change": "-"
    },
    {
        "title": "Destiny’s Memories",
        "ImageURL": "http://tkfile.yes24.com/upload2/perfblog/202412/20241203/20241203-51897.jpg",
        "Venue": "2024.12.12~2025.01.19Aube Studio",
        "rank": "3위",
        "site": "http://ticket.yes24.com/Rank/All",
        "change": "NEW"
    },
    {
        "title": "[부산] 이토 준지 호러하우스",
        "ImageURL": "http://tkfile.yes24.com/upload2/perfblog/202411/20241120/20241120-51786.jpg",
        "Venue": "2024.12.14~2025.06.08DUEX 부산 (더샵센트럴스타 B1)",
        "rank": "4위",
        "change": "-",
        "site": "http://ticket.yes24.com/Rank/All"
    },
    {
        "title": "불멸의 화가 반 고흐",
        "ImageURL": "http://tkfile.yes24.com/upload2/perfblog/202410/20241018/20241018-51395.jpg",
        "Venue": "2024.11.29~2025.03.16예술의전당 한가람미술관 제1,2 전시실",
        "rank": "5위",
        "change": "2단계 상승",
        "site": "http://ticket.yes24.com/Rank/All"
    },
    {
        "title": "[청년문화예술패스] 불멸의 화가 반 고흐",
        "ImageURL": "http://tkfile.yes24.com/upload2/perfblog/202410/20241018/20241018-51395.jpg",
        "Venue": "2024.11.29~2024.12.31예술의전당 한가람미술관 제1,2 전시실",
        "rank": "6위",
        "change": "-",
        "site": "http://ticket.yes24.com/Rank/All"
    },
    {
        "title": "[청년문화예술패스] [부산] 이토 준지 호러하우스",
        "ImageURL": "http://tkfile.yes24.com/upload2/perfblog/202411/20241120/20241120-51786.jpg",
        "Venue": "2024.12.14~2024.12.31DUEX 부산 (더샵센트럴스타 B1)",
        "rank": "7위",
        "change": "3단계 상승",
        "site": "http://ticket.yes24.com/Rank/All"
    },
    {
        "title": "2025 대한민국 라면박람회 패키지",
        "ImageURL": "http://tkfile.yes24.com/upload2/perfblog/202411/20241106/20241106-51623.jpg",
        "Venue": "2025.04.04~2025.04.06코엑스 마곡",
        "rank": "8위",
        "change": "1단계 상승",
        "site": "http://ticket.yes24.com/Rank/All"
    },
    {
        "title": "미피 70주년 생일 기념전: 미피와 마법 우체통",
        "ImageURL": "http://tkfile.yes24.com/upload2/perfblog/202411/20241120/20241120-51562.jpg",
        "Venue": "2024.11.21~2025.08.17안녕 인사동 B1 인사센트럴뮤지엄",
        "rank": "9위",
        "change": "4단계 상승",
        "site": "http://ticket.yes24.com/Rank/All"
    },
    {
        "title": "툴루즈 로트렉 : 몽마르트의 별",
        "ImageURL": "http://tkfile.yes24.com/upload2/perfblog/202409/20240924/20240924-50711.jpg",
        "Venue": "2024.09.14~2025.03.03마이아트뮤지엄",
        "rank": "10위",
        "change": "1단계 상승",
        "site": "http://ticket.yes24.com/Rank/All"
    },
    {
        "title": "[대구] 연재 30주년 기념 명탐정 코난展",
        "ImageURL": "http://tkfile.yes24.com/upload2/perfblog/202410/20241021/20241021-51417.jpg",
        "Venue": "2024.11.08~2025.03.03뮤씨엄 대구점",
        "rank": "11위",
        "change": "3단계 상승",
        "site": "http://ticket.yes24.com/Rank/All"
    },
    {
        "title": "2024 마우스 북페어 클래스 : 우정이라는 원동력",
        "ImageURL": "http://tkfile.yes24.com/upload2/perfblog/202411/20241114/20241114-51719.jpg",
        "Venue": "2024.11.30~2024.12.01KT&G 상상마당 부산 라이브홀",
        "rank": "12위",
        "change": "4단계 하락",
        "site": "http://ticket.yes24.com/Rank/All"
    },
    {
        "title": "2025 라면박물관",
        "ImageURL": "http://tkfile.yes24.com/upload2/perfblog/202411/20241113/20241113-51705.jpeg",
        "Venue": "2025.04.04~2025.04.06코엑스 마곡",
        "rank": "13위",
        "change": "4단계 상승",
        "site": "http://ticket.yes24.com/Rank/All"
    },
    {
        "title": "경희궁 인문학산책",
        "ImageURL": "http://tkfile.yes24.com/upload2/perfblog/202404/20240412/20240412-49451.jpg",
        "Venue": "2024.04.15~2024.12.31경희궁",
        "rank": "14위",
        "change": "12단계 상승",
        "site": "http://ticket.yes24.com/Rank/All"
    },
    {
        "title": "[부산] 독일 현대미술의 거장展：크리스토프 루크헤베를레",
        "ImageURL": "http://tkfile.yes24.com/upload2/perfblog/202408/20240824/20240824-50820.jpg",
        "Venue": "2024.09.14~2025.03.09광안리 포디움 다이브 M",
        "rank": "15위",
        "change": "1단계 상승",
        "site": "http://ticket.yes24.com/Rank/All"
    }
]